Arora/__init__.py
Arora/filter.py
Arora/get_edf.py
Arora/get_segment.py
Arora/get_signals.py
Arora/lower_frequency.py
Arora/math.py
Arora/pair_signals.py
Arora/read_mat.py
Arora/wavelet.py
Arora/core/EEG_freqbands.py
Arora/core/__init__.py
Arora/core/adaptive_segmentation.py
Arora/core/bandpass.py
Arora/core/combine_edf.py
Arora/core/find_features.py
Arora/core/segmentation.py
Arora/core/sleepdata.py
Arora/core/upper_lower_signal_envelopes.py
Antora-0.0.1.dist-info/METADATA
Antora-0.0.1.dist-info/WHEEL
Antora-0.0.1.dist-info/top_level.txt
Antora-0.0.1.dist-info/RECORD
