Metadata-Version: 2.1
Name: Antora
Version: 0.0.1
Summary: A tool for sleep researcher to preprocess, work, analyze and visualize data
Author: Sleep Revolution
Author-email: benedikthth@ru.is, mariaoskars@ru.is
License: UNKNOWN
Platform: UNKNOWN
Classifier: Development Status :: 3 - Alpha
Classifier: Intended Audience :: Science/Research
Classifier: Operating System :: OS Independent
Classifier: Programming Language :: Python :: 3.8
Requires-Python: >=3.8
Requires-Dist: numpy
Requires-Dist: pandas
Requires-Dist: pyEDFlib
Requires-Dist: scipy
